README.md
setup.cfg
setup.py
ndnoise/__init__.py
ndnoise/filtration.py
ndnoise/generator.py
ndnoise.egg-info/PKG-INFO
ndnoise.egg-info/SOURCES.txt
ndnoise.egg-info/dependency_links.txt
ndnoise.egg-info/requires.txt
ndnoise.egg-info/top_level.txt