Metadata-Version: 1.1
Name: ndnoise
Version: 0.0.14
Summary: distribution to pypi and conda
Home-page: https://github.com/mjirik/ndnoise
Author: Miroslav Jirik
Author-email: miroslav.jirik@gmail.com
License: MIT
Keywords: dicom 3D read write
Platform: UNKNOWN
Classifier: Development Status :: 3 - Alpha
Classifier: Intended Audience :: Developers
Classifier: Topic :: Scientific/Engineering :: Bio-Informatics
Classifier: License :: OSI Approved :: BSD License
Classifier: Programming Language :: Python :: 2.7
